mednlp/__init__.py
mednlp/core.py
mednlp/entities.py
mednlp/preprocessing.py
mednlp-0.0.1a1.dist-info/licenses/LICENSE
mednlp-0.0.1a1.dist-info/METADATA
mednlp-0.0.1a1.dist-info/WHEEL
mednlp-0.0.1a1.dist-info/top_level.txt
mednlp-0.0.1a1.dist-info/RECORD
